body_measurements/measurement.py
body_measurements-1.1.1.dist-info/LICENSE
body_measurements-1.1.1.dist-info/METADATA
body_measurements-1.1.1.dist-info/WHEEL
body_measurements-1.1.1.dist-info/top_level.txt
body_measurements-1.1.1.dist-info/RECORD
