Metadata-Version: 2.1
Name: body-measurements
Version: 1.1.1
Summary: It allows us to measure the human body generated by SMPL model.
Home-page: https://github.com/vcarlosrb/3d-body-measurements
Author: Carlos Roca
Author-email: u2carlosroca@gmail.com
License: MIT License
Download-URL: https://github.com/vcarlosrb/3d-body-measurements/tarball/0.1
Keywords: body,measurements,SMPL
Platform: UNKNOWN
Requires-Python: >=3.8
License-File: LICENSE
Requires-Dist: trimesh (>=3.8.8)
Requires-Dist: numpy (>=1.19.1)
Requires-Dist: scipy (>=1.5.2)
Requires-Dist: shapely (>=1.7.1)
Requires-Dist: networkx (>=2.5)
